datalab_api/__init__.py
datalab_api/_base.py
datalab_api/cli.py
datalab_api/helpers.py
datalab_api/utils.py
datalab_api-0.3.0.dist-info/licenses/LICENSE
datalab_api-0.3.0.dist-info/METADATA
datalab_api-0.3.0.dist-info/WHEEL
datalab_api-0.3.0.dist-info/entry_points.txt
datalab_api-0.3.0.dist-info/top_level.txt
datalab_api-0.3.0.dist-info/RECORD
