Metadata-Version: 2.4
Name: datalab-api
Version: 0.3.0
Summary: A Python API for instances of the datalab data management platform (https://github.com/datalab-org/datalab).
Author-email: Matthew Evans <matthew@ml-evs.science>
License-Expression: MIT
Project-URL: homepage, https://github.com/datalab-org/datalab-api
Project-URL: repository, https://github.com/datalab-org/datalab-api
Project-URL: documentation, https://datalab-python-api.readthedocs.io
Project-URL: changelog, https://github.com/datalab-org/datalab-api/releases
Classifier: Programming Language :: Python :: 3
Classifier: Programming Language :: Python :: 3.9
Classifier: Programming Language :: Python :: 3.10
Classifier: Programming Language :: Python :: 3.11
Classifier: Programming Language :: Python :: 3.12
Classifier: Intended Audience :: Science/Research
Classifier: Intended Audience :: Information Technology
Classifier: Topic :: Other/Nonlisted Topic
Classifier: Topic :: Scientific/Engineering
Requires-Python: >=3.9
License-File: LICENSE
Requires-Dist: httpx~=0.28
Requires-Dist: bokeh~=2.4; platform_system != "Emscripten"
Requires-Dist: rich~=13.0
Requires-Dist: numpy<2
Provides-Extra: dev
Requires-Dist: pre-commit<5,>=3; extra == "dev"
Requires-Dist: pytest~=8.0; extra == "dev"
Requires-Dist: pytest-cov<7,>=5; extra == "dev"
Requires-Dist: respx~=0.22; extra == "dev"
Provides-Extra: docs
Requires-Dist: mkdocs; extra == "docs"
Requires-Dist: mkdocs-material; extra == "docs"
Requires-Dist: mkdocstrings[python-legacy]; extra == "docs"
Requires-Dist: mkdocs-awesome-pages-plugin; extra == "docs"
Requires-Dist: mkdocs-jupyter; extra == "docs"
Provides-Extra: cli
Requires-Dist: typer~=0.9; extra == "cli"
Requires-Dist: click-shell~=2.1; extra == "cli"
Provides-Extra: cheminventory-helper
Requires-Dist: pandas~=2.2; extra == "cheminventory-helper"
Requires-Dist: openpyxl~=3.0; extra == "cheminventory-helper"
Provides-Extra: all
Requires-Dist: datalab-api[cli,dev,docs]; extra == "all"
Dynamic: license-file
